evtx2es/__init__.py
evtx2es/models/ElasticsearchUtils.py
evtx2es/models/Evtx2es.py
evtx2es/models/MetaData.py
evtx2es/presenters/Evtx2esPresenter.py
evtx2es/presenters/Evtx2jsonPresenter.py
evtx2es/views/BaseView.py
evtx2es/views/Evtx2esView.py
evtx2es/views/Evtx2jsonView.py
evtx2es-1.8.0.dist-info/METADATA
evtx2es-1.8.0.dist-info/WHEEL
evtx2es-1.8.0.dist-info/entry_points.txt
evtx2es-1.8.0.dist-info/licenses/LICENSE
evtx2es-1.8.0.dist-info/RECORD
