Metadata-Version: 2.4
Name: evtx2es
Version: 1.8.0
Summary: A library for fast parse & import of Windows Eventlogs into Elasticsearch.
Author-email: sumeshi <sum3sh1@protonmail.com>
License-Expression: MIT
License-File: LICENSE
Requires-Python: >=3.11
Requires-Dist: elasticsearch>=9.0.2
Requires-Dist: evtx>=0.8.9
Requires-Dist: orjson>=3.10.18
Requires-Dist: tqdm>=4.67.1
Requires-Dist: urllib3>=2.4.0
